cmc_csci046_rgao23_containers-1.0.0.dist-info/DESCRIPTION.rst
cmc_csci046_rgao23_containers-1.0.0.dist-info/METADATA
cmc_csci046_rgao23_containers-1.0.0.dist-info/RECORD
cmc_csci046_rgao23_containers-1.0.0.dist-info/WHEEL
cmc_csci046_rgao23_containers-1.0.0.dist-info/metadata.json
cmc_csci046_rgao23_containers-1.0.0.dist-info/top_level.txt
containers/AVLTree.py
containers/BST.py
containers/BinaryTree.py
containers/Heap.py
containers/fibonacci.py
containers/range.py
containers/unicode.py
