Metadata-Version: 2.0
Name: cmc-csci046-rgao23-containers
Version: 1.0.0
Summary: CSCI046 HW -- Data Structures and Algorithms course package
Home-page: https://github.com/RuiluGao/containers
Author: Ruilu Gao
Author-email: rgao23@cmc.edu
License: MIT
Platform: UNKNOWN
Classifier: License :: OSI Approved :: MIT License
Classifier: Programming Language :: Python :: 3
Classifier: Programming Language :: Python :: 3.7
Requires-Dist: pytest
Requires-Dist: hypothesis
